csklearn/__init__.py
csklearn/improving_naive_bayes.py
csklearn/topsis.py
csklearing-0.0.1.dist-info/METADATA
csklearing-0.0.1.dist-info/WHEEL
csklearing-0.0.1.dist-info/top_level.txt
csklearing-0.0.1.dist-info/RECORD
