Metadata-Version: 2.1
Name: csklearing
Version: 0.0.1
Summary: 自己平时会使用的一些统计学和数学模型
Author: Checkey01
Author-email: Chiaki2048@outlook.com
Keywords: Machine Learning,Python
Requires-Dist: numpy
Requires-Dist: pandas
Requires-Dist: scikit-learn
